odoo/addons/hr_timesheet_report/README.rst
odoo/addons/hr_timesheet_report/__init__.py
odoo/addons/hr_timesheet_report/__manifest__.py
odoo/addons/hr_timesheet_report/i18n/fr.po
odoo/addons/hr_timesheet_report/i18n/hr_timesheet_report.pot
odoo/addons/hr_timesheet_report/i18n/it.po
odoo/addons/hr_timesheet_report/i18n/pt.po
odoo/addons/hr_timesheet_report/models/__init__.py
odoo/addons/hr_timesheet_report/models/account_analytic_line.py
odoo/addons/hr_timesheet_report/readme/CONTRIBUTORS.rst
odoo/addons/hr_timesheet_report/readme/DESCRIPTION.rst
odoo/addons/hr_timesheet_report/readme/USAGE.rst
odoo/addons/hr_timesheet_report/report/__init__.py
odoo/addons/hr_timesheet_report/report/hr_timesheet_report.py
odoo/addons/hr_timesheet_report/report/hr_timesheet_report.xml
odoo/addons/hr_timesheet_report/security/ir.model.access.csv
odoo/addons/hr_timesheet_report/static/description/icon.png
odoo/addons/hr_timesheet_report/static/description/index.html
odoo/addons/hr_timesheet_report/tests/__init__.py
odoo/addons/hr_timesheet_report/tests/test_hr_timesheet_report.py
odoo/addons/hr_timesheet_report/views/account_analytic_line.xml
odoo/addons/hr_timesheet_report/wizards/__init__.py
odoo/addons/hr_timesheet_report/wizards/hr_timesheet_report_wizard.py
odoo/addons/hr_timesheet_report/wizards/hr_timesheet_report_wizard.xml
odoo14_addon_hr_timesheet_report-14.0.1.0.1.dist-info/METADATA
odoo14_addon_hr_timesheet_report-14.0.1.0.1.dist-info/WHEEL
odoo14_addon_hr_timesheet_report-14.0.1.0.1.dist-info/top_level.txt
odoo14_addon_hr_timesheet_report-14.0.1.0.1.dist-info/RECORD
